brother_label_printer/__init__.py
brother_label_printer/items.py
brother_label_printer/label.py
brother_label_printer/backends/__init__.py
brother_label_printer/printers/__init__.py
brother_label_printer/printers/brother_pt700.py
brother_label_printer-0.0.6.dist-info/LICENSE
brother_label_printer-0.0.6.dist-info/METADATA
brother_label_printer-0.0.6.dist-info/WHEEL
brother_label_printer-0.0.6.dist-info/top_level.txt
brother_label_printer-0.0.6.dist-info/RECORD
