Metadata-Version: 2.1
Name: brother-label-printer
Version: 0.0.6
Summary: A library for creating and printing labels
Home-page: https://github.com/Avi-Singh12/labelprinterkit.git
Author: Avi Singh
Author-email: singhavi@umich.edu
License: Apache License, Version 2.0
Platform: UNKNOWN
Classifier: Programming Language :: Python :: 3
Classifier: Programming Language :: Python :: 3.5
Classifier: Programming Language :: Python :: 3.6
Requires-Python: >=3.4
Requires-Dist: pillow
Requires-Dist: pyusb
Requires-Dist: packbits
Requires-Dist: pyserial
Requires-Dist: qrcode
